cg_lims/__init__.py
cg_lims/exceptions.py
cg_lims/objects.py
cg_lims/options.py
cg_lims/status_db_api.py
cg_lims/EPPs/__init__.py
cg_lims/EPPs/base.py
cg_lims/EPPs/arnold/__init__.py
cg_lims/EPPs/arnold/base.py
cg_lims/EPPs/arnold/flow_cell.py
cg_lims/EPPs/arnold/prep.py
cg_lims/EPPs/arnold/sample.py
cg_lims/EPPs/arnold/sequencing.py
cg_lims/EPPs/files/__init__.py
cg_lims/EPPs/files/barcode_tubes.py
cg_lims/EPPs/files/base.py
cg_lims/EPPs/files/file_to_udf.py
cg_lims/EPPs/files/csv_for_kapa_truble_shooting/__init__.py
cg_lims/EPPs/files/csv_for_kapa_truble_shooting/csv_for_kapa_debug.py
cg_lims/EPPs/files/csv_for_kapa_truble_shooting/models.py
cg_lims/EPPs/files/hamilton/__init__.py
cg_lims/EPPs/files/hamilton/base.py
cg_lims/EPPs/files/hamilton/buffer_exchange_twist_file.py
cg_lims/EPPs/files/hamilton/make_kapa_csv.py
cg_lims/EPPs/files/hamilton/models.py
cg_lims/EPPs/files/hamilton/normalization_file.py
cg_lims/EPPs/files/hamilton/sars_cov2_prep_file.py
cg_lims/EPPs/files/placement_map/__init__.py
cg_lims/EPPs/files/placement_map/hmtl_templates.py
cg_lims/EPPs/files/placement_map/make_96well_placement_map.py
cg_lims/EPPs/files/placement_map/models.py
cg_lims/EPPs/files/pooling_map/__init__.py
cg_lims/EPPs/files/pooling_map/hmtl_templates.py
cg_lims/EPPs/files/pooling_map/make_pooling_map.py
cg_lims/EPPs/files/pooling_map/models.py
cg_lims/EPPs/move/__init__.py
cg_lims/EPPs/move/base.py
cg_lims/EPPs/move/move_samples.py
cg_lims/EPPs/move/place_samples_in_seq_agg.py
cg_lims/EPPs/move/rerun_samples.py
cg_lims/EPPs/qc/__init__.py
cg_lims/EPPs/qc/base.py
cg_lims/EPPs/qc/set_qc_fail.py
cg_lims/EPPs/udf/__init__.py
cg_lims/EPPs/udf/base.py
cg_lims/EPPs/udf/calculate/__init__.py
cg_lims/EPPs/udf/calculate/base.py
cg_lims/EPPs/udf/calculate/calculate_amount_ng.py
cg_lims/EPPs/udf/calculate/calculate_average_size_and_set_qc.py
cg_lims/EPPs/udf/calculate/calculate_beads.py
cg_lims/EPPs/udf/calculate/calculate_microbial_aliquot_volumes.py
cg_lims-6.8.0.dist-info/METADATA
cg_lims-6.8.0.dist-info/WHEEL
cg_lims-6.8.0.dist-info/entry_points.txt
cg_lims-6.8.0.dist-info/top_level.txt
cg_lims-6.8.0.dist-info/RECORD
