Metadata-Version: 2.1
Name: cg-lims
Version: 6.8.0
Summary: Lims code for Clinical Genomics
Home-page: https://github.com/Clinical-Genomics/cg_lims
Author: Maya Brandi
Author-email: maya.brandi@scilifelab.se
License: UNKNOWN
Platform: UNKNOWN
Classifier: Programming Language :: Python :: 3
Classifier: License :: OSI Approved :: MIT License
Classifier: Operating System :: OS Independent
Requires-Python: >=3.6
